imddaily/__init__.py
imddaily/core.py
imddaily/imddaily.py
imddaily-0.3.0.dist-info/LICENSE.txt
imddaily-0.3.0.dist-info/METADATA
imddaily-0.3.0.dist-info/WHEEL
imddaily-0.3.0.dist-info/top_level.txt
imddaily-0.3.0.dist-info/RECORD
