Metadata-Version: 2.1
Name: imddaily
Version: 0.3.0
Summary: Download and Convert IMD Daily Data
Author-email: Balakumaran <balakumaran247@gmail.com>
License: MIT License
Project-URL: Homepage, https://github.com/balakumaran247/imddaily
Keywords: IMD,India Meteorological Department,imdpune,Rainfall,Temperature,Precipitation
Classifier: License :: OSI Approved :: MIT License
Classifier: Programming Language :: Python
Classifier: Programming Language :: Python :: 3
Requires-Python: >=3.7
License-File: LICENSE.txt
Requires-Dist: tqdm
Requires-Dist: requests
Requires-Dist: affine
Requires-Dist: numpy
Requires-Dist: gdal
Requires-Dist: rasterio
Provides-Extra: dev
Requires-Dist: black ; extra == 'dev'
Requires-Dist: pytest ; extra == 'dev'
